rcsb/__init__.py
rcsb/db/__init__.py
rcsb/db/cli/ETLExec.py
rcsb/db/cli/RepoHoldingsEtlWorker.py
rcsb/db/cli/RepoLoadExec.py
rcsb/db/cli/RepoScanExec.py
rcsb/db/cli/SchemaUpdateExec.py
rcsb/db/cli/SequenceClustersEtlWorker.py
rcsb/db/cli/__init__.py
rcsb/db/cockroach/CockroachDbLoader.py
rcsb/db/cockroach/CockroachDbUtil.py
rcsb/db/cockroach/Connection.py
rcsb/db/cockroach/__init__.py
rcsb/db/crate/Connection.py
rcsb/db/crate/CrateDbLoader.py
rcsb/db/crate/CrateDbUtil.py
rcsb/db/crate/__init__.py
rcsb/db/define/ContentDefinition.py
rcsb/db/define/DataTypeApiProvider.py
rcsb/db/define/DataTypeApplicationInfo.py
rcsb/db/define/DataTypeInstanceInfo.py
rcsb/db/define/SchemaDefAccess.py
rcsb/db/define/SchemaDefBuild.py
rcsb/db/define/__init__.py
rcsb/db/helpers/ContentDefinitionHelper.py
rcsb/db/helpers/DocumentDefinitionHelper.py
rcsb/db/helpers/__init__.py
rcsb/db/helpers/r.py
rcsb/db/mongo/Connection.py
rcsb/db/mongo/ConnectionBase.py
rcsb/db/mongo/DocumentLoader.py
rcsb/db/mongo/MongoDbUtil.py
rcsb/db/mongo/PdbxLoader.py
rcsb/db/mongo/__init__.py
rcsb/db/mysql/Connection.py
rcsb/db/mysql/ConnectionBase.py
rcsb/db/mysql/MyDbAdapter.py
rcsb/db/mysql/MyDbUtil.py
rcsb/db/mysql/MysqlSchemaImporter.py
rcsb/db/mysql/SchemaDefLoader.py
rcsb/db/mysql/__init__.py
rcsb/db/processors/ClusterDataPrep.py
rcsb/db/processors/DataExchangeStatus.py
rcsb/db/processors/DataTransformFactory.py
rcsb/db/processors/RepoHoldingsDataPrep.py
rcsb/db/processors/SchemaDefDataPrep.py
rcsb/db/processors/SchemaDefReShape.py
rcsb/db/processors/__init__.py
rcsb/db/sql/QueryDirectives.py
rcsb/db/sql/SqlGen.py
rcsb/db/sql/__init__.py
rcsb/db/utils/CaseNormalizedDict.py
rcsb/db/utils/PdbxSchemaMapReader.py
rcsb/db/utils/ProvenanceProvider.py
rcsb/db/utils/SchemaProvider.py
rcsb/db/utils/TextUtil.py
rcsb/db/utils/TimeUtil.py
rcsb/db/utils/__init__.py
rcsb/db/utils/makePathList.py
rcsb/db/utils/unescape.py
rcsb/db/wf/RepoLoadWorkflow.py
rcsb/db/wf/__init__.py
rcsb.db-1.676.dist-info/LICENSE
rcsb.db-1.676.dist-info/METADATA
rcsb.db-1.676.dist-info/WHEEL
rcsb.db-1.676.dist-info/entry_points.txt
rcsb.db-1.676.dist-info/top_level.txt
rcsb.db-1.676.dist-info/RECORD
