Metadata-Version: 2.1
Name: rcsb.db
Version: 1.676
Summary: RCSB Python Database Access and Loading Utility Classes
Home-page: https://github.com/rcsb/py-rcsb_db
Author: John Westbrook
Author-email: john.westbrook@rcsb.org
License: Apache 2.0
Platform: UNKNOWN
Classifier: Development Status :: 4 - Beta
Classifier: Intended Audience :: Developers
Classifier: Natural Language :: English
Classifier: License :: OSI Approved :: Apache Software License
Classifier: Programming Language :: Python
Classifier: Programming Language :: Python :: 2.7
Classifier: Programming Language :: Python :: 3
Classifier: Programming Language :: Python :: 3.9
Requires-Dist: future
Requires-Dist: six
Requires-Dist: python-dateutil
Requires-Dist: pytz
Requires-Dist: jsonschema (>=2.6.0)
Requires-Dist: jsondiff (>=1.2.0)
Requires-Dist: strict-rfc3339
Requires-Dist: mysqlclient (>=1.3.12)
Requires-Dist: pymongo (>=3.7.0)
Requires-Dist: mmcif (>=0.70)
Requires-Dist: rcsb.utils.config (>=0.35)
Requires-Dist: rcsb.utils.io (>=1.12)
Requires-Dist: rcsb.utils.multiproc (>=0.18)
Requires-Dist: rcsb.utils.chemref (>=0.72)
Requires-Dist: rcsb.utils.dictionary (>=0.40)
Requires-Dist: rcsb.utils.repository (>=0.16)
Requires-Dist: crate
Requires-Dist: psycopg2-binary
Requires-Dist: scandir ; python_version < "3.0"
Requires-Dist: configparser ; python_version < "3.0"
Requires-Dist: SQLAlchemy ; sys_platform == "linux"
Provides-Extra: dev
Requires-Dist: check-manifest ; extra == 'dev'
Provides-Extra: test
Requires-Dist: coverage ; extra == 'test'
